enzo/__init__.py
enzo/activations.py
enzo/derivatives.py
enzo/docstrings.py
enzo/exceptions.py
enzo/layers.py
enzo/loss.py
enzo/losses.py
enzo/models.py
enzo/units.py
enzo-0.0.1.dev6.dist-info/LICENSE
enzo-0.0.1.dev6.dist-info/METADATA
enzo-0.0.1.dev6.dist-info/WHEEL
enzo-0.0.1.dev6.dist-info/top_level.txt
enzo-0.0.1.dev6.dist-info/RECORD
