Metadata-Version: 2.1
Name: enzo
Version: 0.0.1.dev6
Summary: A neural network library designed from scratch.
Home-page: https://github.com/thomasbreydo/enzo
Author: Thomas Breydo
Author-email: tbreydo@gmail.com
License: UNKNOWN
Project-URL: Code, https://github.com/thomasbreydo/enzo
Project-URL: Documentation, https://enzo-docs.readthedocs.io
Platform: UNKNOWN
Classifier: Development Status :: 3 - Alpha
Classifier: License :: OSI Approved :: GNU General Public License v3 (GPLv3)
Classifier: Operating System :: OS Independent
Classifier: Programming Language :: Python
Classifier: Topic :: Scientific/Engineering :: Artificial Intelligence
Requires-Python: >=3.6
Requires-Dist: numpy (==1.19.0)
